{
  "389801252": [
    {
      "appId": "389801252",
      "id": "14066662078",
      "author": "Jjjaaammmiiieeee",
      "title": "Disgusting amount of ads and suggested content is annoying",
      "body": "POV: You open your feed to a sponsored post. You scroll to see friends/accounts you follow but instead see random suggested accounts. You go to stories because they used to be more up to date… NOPE more suggested content and ads you don’t want. \n\nY’all are becoming as trashy and dumb as snapchat",
      "score": 1,
      "updatedAt": "2026-05-15T03:35:33-07:00",
      "deletedAt": null
    },
    {
      "appId": "389801252",
      "id": "14066626321",
      "author": "Sid Vaga",
      "title": "What!?",
      "body": "The app is confusing, hard to navigate, not intuitive at all.",
      "score": 1,
      "updatedAt": "2026-05-15T03:21:23-07:00",
      "deletedAt": null
    },
    {
      "appId": "389801252",
      "id": "14066605845",
      "author": "Bbb.bk",
      "title": "اسوء شركة",
      "body": "سيء جدا",
      "score": 1,
      "updatedAt": "2026-05-15T03:13:01-07:00",
      "deletedAt": null
    },
    {
      "appId": "389801252",
      "id": "14066602085",
      "author": "Chaeli Pablo",
      "title": "instants",
      "body": "It's really annoying when apps keep pushing out updates that don't actually improve anything. Like that \"instants\" thing they added, what was the point? Everyone just ends up taking the same picture like five to seven times to get it right, and it totally bogs down the whole process. It feels like they're just churning out updates for the sake of it, rather than focusing on making the app genuinely better or more intuitive. It's a shame because sometimes these apps have potential, but then they make these weird, useless changes that just make you want to uninstall them.",
      "score": 1,
      "updatedAt": "2026-05-15T03:11:27-07:00",
      "deletedAt": null
    },
    {
      "appId": "389801252",
      "id": "14066585116",
      "author": "Rocío49",
      "title": "Lulu’s",
      "body": "Una de las mejores aplicaciones que tengo",
      "score": 5,
      "updatedAt": "2026-05-15T03:04:28-07:00",
      "deletedAt": null
    },
    {
      "appId": "389801252",
      "id": "14066584889",
      "author": "Idontknowwth123",
      "title": "Instagram",
      "body": "I love instagram but can we get rid of this instant thingy? It’s taking up so much space.",
      "score": 5,
      "updatedAt": "2026-05-15T03:04:22-07:00",
      "deletedAt": null
    },
    {
      "appId": "389801252",
      "id": "14066545813",
      "author": "boogeyky",
      "title": "good",
      "body": "the updating is inconsistent, something’s it’ll downgrade the update after months, you’ll no longer be able to use the feature that’s available to everyone else. Also inconsistent features across different accounts.",
      "score": 3,
      "updatedAt": "2026-05-15T02:47:53-07:00",
      "deletedAt": null
    },
    {
      "appId": "389801252",
      "id": "14066503911",
      "author": "6263:",
      "title": "Ban Wave",
      "body": "Banning multiple accounts nobody is safe",
      "score": 1,
      "updatedAt": "2026-05-15T02:29:27-07:00",
      "deletedAt": null
    },
    {
      "appId": "389801252",
      "id": "14066450471",
      "author": "lingaoyi",
      "title": "垃圾app，随便封了我的14年帐号。",
      "body": "Request for Review of Disabled Instagram Account(lingaoyi)",
      "score": 1,
      "updatedAt": "2026-05-15T02:05:38-07:00",
      "deletedAt": null
    },
    {
      "appId": "389801252",
      "id": "14066362746",
      "author": "✌🏻 PEACE OUT",
      "title": "):",
      "body": "do people still use this platform nowadays because feels like it is slowly dying",
      "score": 5,
      "updatedAt": "2026-05-15T01:24:41-07:00",
      "deletedAt": null
    },
    {
      "appId": "389801252",
      "id": "14066319439",
      "author": "Yannicklifts",
      "title": "Thanks",
      "body": "Thank you instagram",
      "score": 5,
      "updatedAt": "2026-05-15T01:04:11-07:00",
      "deletedAt": null
    },
    {
      "appId": "389801252",
      "id": "14066233579",
      "author": "bullethead82",
      "title": "Love IG",
      "body": "Love being able to reach the masses with love so we can help so many people",
      "score": 5,
      "updatedAt": "2026-05-15T00:22:50-07:00",
      "deletedAt": null
    },
    {
      "appId": "389801252",
      "id": "14066185928",
      "author": "cod.ybrendan",
      "title": "Account got Wrongfully Disabled",
      "body": "I’m giving Instagram 1 star based on my personal experience with account restrictions and suspensions. My original account of all my memories and connections and followers and school organizations was wrongfully disabled, and when I tried to create a new one, it kept getting flagged as well, which made it really difficult to stay on the platform. \n\nWhat’s been the hardest part is not just losing access, but losing all the memories connected to my account. Over time, my Instagram became a place where I kept important milestones, conversations, and connections with friends and people I care about. It honestly feels like a digital part of my life just got cut off.\n\nI understand platforms need safety systems and rules, but the process feels very automated and unclear, and it’s hard to know what went wrong or how to properly fix it. I’ve tried appeals and different steps, but I still haven’t been able to recover my original account.\n\nI just hope there can be a more transparent and fair way for users to regain access, especially when their account holds so many personal memories. I really hope to gain justice and get my account @cod.ybrendan back. I am very upset for the valuable losses I faced in the past week , and I want to talk to a human at meta to resolve and gain my disabled account.",
      "score": 1,
      "updatedAt": "2026-05-14T23:59:59-07:00",
      "deletedAt": null
    },
    {
      "appId": "389801252",
      "id": "14066168526",
      "author": "iisn1",
      "title": "Update won’t work",
      "body": "The updates on my main account don’t work. Only when I use my other account they show the features, not on my main acc",
      "score": 4,
      "updatedAt": "2026-05-14T23:51:22-07:00",
      "deletedAt": null
    },
    {
      "appId": "389801252",
      "id": "14066152090",
      "author": "Gggijgg",
      "title": "They keep deleting my instagram quando.quan for no reason",
      "body": "They will delete your instagram for no reason and will not tell you why plus they do not have a customer service team everything is ranned by AI this sucks! FACEBOOK IS BETTER",
      "score": 1,
      "updatedAt": "2026-05-14T23:43:13-07:00",
      "deletedAt": null
    },
    {
      "appId": "389801252",
      "id": "14066146212",
      "author": "ler mu dex",
      "title": "Instagram",
      "body": "I like using instagram because I been talking to people a lot",
      "score": 5,
      "updatedAt": "2026-05-14T23:40:19-07:00",
      "deletedAt": null
    },
    {
      "appId": "389801252",
      "id": "14066133563",
      "author": "piñacada23",
      "title": "Meta AI wrongfully banning accounts for falsely accusing of CSE",
      "body": "I think it’s already about time to fix this huge issue with Meta which has left hundreds of thousands of people with their account permanently disabled. Zero stars 👎🏻",
      "score": 1,
      "updatedAt": "2026-05-14T23:34:00-07:00",
      "deletedAt": null
    },
    {
      "appId": "389801252",
      "id": "14066067158",
      "author": "SinaiGuide",
      "title": "Сафари и каньон и город Дахаб и море",
      "body": "Бомба ⭐️⭐️🫶🏻",
      "score": 5,
      "updatedAt": "2026-05-14T23:00:50-07:00",
      "deletedAt": null
    },
    {
      "appId": "389801252",
      "id": "14066064687",
      "author": "Rousy reseña ig",
      "title": "Instagram",
      "body": "Es muy buena aplicación lo malo es que te suspenden tu cuenta si tú hacer nada malo nada más porque si y cuando te intentas crear otra no llevas ni una hora con esa cuenta y te la vuelven a suspender y eso estresa aunque es muy buena,sus errores son malos y debes esperar meses para que te acepten tu rostro y datos para ver si te devuelven tu cuente que horror aunque a la vez es buena por sus funciones pero solo ese error hace que no sea 100% la mejor aplicación.",
      "score": 3,
      "updatedAt": "2026-05-14T22:59:36-07:00",
      "deletedAt": null
    },
    {
      "appId": "389801252",
      "id": "14066032110",
      "author": "Mr. Ricooo",
      "title": "Awful",
      "body": "Ruined my relationship because the stupid app removed a highlight on “accident”",
      "score": 1,
      "updatedAt": "2026-05-14T22:42:59-07:00",
      "deletedAt": null
    },
    {
      "appId": "389801252",
      "id": "14065992546",
      "author": "Ashley-Lauren🌺✨",
      "title": "MUSIC ON POSTS",
      "body": "There should be an option for users to edit a song they have on a post. Especially when the original song you put on a post is no longer available!!! Ruins the aesthetic 🙄",
      "score": 3,
      "updatedAt": "2026-05-14T22:22:52-07:00",
      "deletedAt": null
    },
    {
      "appId": "389801252",
      "id": "14065969518",
      "author": "DeeLeeRokkz",
      "title": "STOP THE AI META",
      "body": "Thanks a ton for deleting my main profile and Facebook. Shame.",
      "score": 1,
      "updatedAt": "2026-05-14T22:11:03-07:00",
      "deletedAt": null
    },
    {
      "appId": "389801252",
      "id": "14065925786",
      "author": "Elenia Holy journey",
      "title": "Beast Mode",
      "body": "Whether you are posting a family event, night out, business adventure- instagram provide you with so many options to help your post be fabulous, text- music- effects are outstanding.easy for any age to use.",
      "score": 5,
      "updatedAt": "2026-05-14T21:48:47-07:00",
      "deletedAt": null
    },
    {
      "appId": "389801252",
      "id": "14065925068",
      "author": "MissMiniMoo",
      "title": "Story progress bar",
      "body": "Show the story progress bar at the top again instead of the bottom",
      "score": 3,
      "updatedAt": "2026-05-14T21:48:25-07:00",
      "deletedAt": null
    },
    {
      "appId": "389801252",
      "id": "14065845318",
      "author": "𝓐𝓻𝓪𝓶 °.✩┈┈∘*┈୨୧┈*∘┈┈✩.°",
      "title": "it is really good",
      "body": "it’s really good because it’s really easy to work with and it doesn’t have that much bad videos and you can post anything you want so good\nand if you wanna follow me, just search ARAM",
      "score": 5,
      "updatedAt": "2026-05-14T21:08:46-07:00",
      "deletedAt": null
    },
    {
      "appId": "389801252",
      "id": "14065841707",
      "author": "JackieBarajasM",
      "title": "Too much going on",
      "body": "Now theres something at the corner thats essentially another story? So annoying",
      "score": 2,
      "updatedAt": "2026-05-14T21:06:58-07:00",
      "deletedAt": null
    },
    {
      "appId": "389801252",
      "id": "14065823436",
      "author": "Restringuir111",
      "title": "RESTRICCIÓN",
      "body": "POR FAVOR COLOQUEN OPCIÓN PARA RESTRINGIR SEGUIDORES Y SEGUIDOS",
      "score": 3,
      "updatedAt": "2026-05-14T20:58:04-07:00",
      "deletedAt": null
    },
    {
      "appId": "389801252",
      "id": "14065816702",
      "author": "CurvedApple6693",
      "title": "Dookie",
      "body": "It won’t dookie update",
      "score": 1,
      "updatedAt": "2026-05-14T20:54:50-07:00",
      "deletedAt": null
    },
    {
      "appId": "389801252",
      "id": "14065810220",
      "author": "ewwles",
      "title": "👎",
      "body": "literal bad",
      "score": 2,
      "updatedAt": "2026-05-14T20:51:40-07:00",
      "deletedAt": null
    },
    {
      "appId": "389801252",
      "id": "14065789443",
      "author": "-;7473$;!,$;",
      "title": "Good",
      "body": "My address got leaked, they robbed me, took my belongings, and took my food, wouldn’t recommend.",
      "score": 1,
      "updatedAt": "2026-05-14T20:41:28-07:00",
      "deletedAt": null
    },
    {
      "appId": "389801252",
      "id": "14065783231",
      "author": "Jackiechichi12",
      "title": "I don’t want your ai stop making me use it",
      "body": "I don’t want to use your ai, the fact that you are literally forcing people to use it when they search any is proof that it is bad and you should realize it is and stop shoving it down our throats, you won’t even let us turn it off, you are pathetic",
      "score": 1,
      "updatedAt": "2026-05-14T20:38:28-07:00",
      "deletedAt": null
    },
    {
      "appId": "389801252",
      "id": "14065778435",
      "author": "GingerLuko",
      "title": "Get rid of instants",
      "body": "It sucks",
      "score": 1,
      "updatedAt": "2026-05-14T20:36:12-07:00",
      "deletedAt": null
    },
    {
      "appId": "389801252",
      "id": "14065771871",
      "author": "RustyRayWay",
      "title": "Cannot Scroll Through Comments",
      "body": "When you try scrolling through comments, it tries to make you reply to other people’s comments rather than actually scrolling. This issue alone doesn’t give Instagram a one star rating to me, but I want this review to reach the developers in order to solve this problem. I will reverse my review when the problem has been resolved thank you very much.",
      "score": 1,
      "updatedAt": "2026-05-14T20:33:02-07:00",
      "deletedAt": null
    },
    {
      "appId": "389801252",
      "id": "14065760596",
      "author": "Be1law",
      "title": "Good",
      "body": "They should make and option to change the songs on posts. But good other wise",
      "score": 5,
      "updatedAt": "2026-05-14T20:27:37-07:00",
      "deletedAt": null
    },
    {
      "appId": "389801252",
      "id": "14065752192",
      "author": "IanNoe2027",
      "title": "It is amazing",
      "body": "Love it. Hate it. It doesn’t care. The best place to share moments of your life that will live forever. I wish I had sold vidify to meta years ago. But hindsight is 20/20.",
      "score": 5,
      "updatedAt": "2026-05-14T20:23:38-07:00",
      "deletedAt": null
    },
    {
      "appId": "389801252",
      "id": "14065751224",
      "author": "Thisisduanec",
      "title": "Terrible new features / Public Testing",
      "body": "This app is just getting worse and worse. First they messed up the whole grid sizing, then they add some lame repost button, then they add a stalker map! Like who is running the show over there? Instagrams algorithm is all creepy now and showing me weird stuff, teetering on the edge of very inappropriate! Mean while, all anyone ever wants is either more pins OR to be able to rearrange their photo grids! The rest of these features are either concerning or completely unnecessary! The fact that they roll out partial code and features to random clients / public to do their testing shows their complete lack of confidence in their QE/ Development Team!",
      "score": 2,
      "updatedAt": "2026-05-14T20:23:11-07:00",
      "deletedAt": null
    },
    {
      "appId": "389801252",
      "id": "14065745891",
      "author": "Fat chud man",
      "title": "Bot killed me",
      "body": "A damn bot suspended me then disabled my account without a single person actually looking and now I can’t appeal unless I take it to court, account of 8 years got just like that",
      "score": 1,
      "updatedAt": "2026-05-14T20:20:40-07:00",
      "deletedAt": null
    },
    {
      "appId": "389801252",
      "id": "14065744912",
      "author": "DankDogeDude",
      "title": "Chats are no longer encrypted…",
      "body": "This sucks",
      "score": 1,
      "updatedAt": "2026-05-14T20:20:13-07:00",
      "deletedAt": null
    },
    {
      "appId": "389801252",
      "id": "14065693764",
      "author": "Paying for storage.3",
      "title": ".",
      "body": "Hate new update",
      "score": 1,
      "updatedAt": "2026-05-14T19:56:29-07:00",
      "deletedAt": null
    },
    {
      "appId": "389801252",
      "id": "14065646962",
      "author": "Babbabscf76;447!;!@",
      "title": "Bad new feature",
      "body": "Bad",
      "score": 1,
      "updatedAt": "2026-05-14T19:35:15-07:00",
      "deletedAt": null
    },
    {
      "appId": "389801252",
      "id": "14065645209",
      "author": "Dreamayamni",
      "title": "Natives",
      "body": "Natives",
      "score": 5,
      "updatedAt": "2026-05-14T19:34:28-07:00",
      "deletedAt": null
    },
    {
      "appId": "389801252",
      "id": "14065637986",
      "author": "wnkxkxkk",
      "title": "Restore the feature",
      "body": "please restore the grid editing feature",
      "score": 5,
      "updatedAt": "2026-05-14T19:31:17-07:00",
      "deletedAt": null
    },
    {
      "appId": "389801252",
      "id": "14065636063",
      "author": "image2155555",
      "title": "Y’all be doing too much 😒",
      "body": "…",
      "score": 1,
      "updatedAt": "2026-05-14T19:30:23-07:00",
      "deletedAt": null
    },
    {
      "appId": "389801252",
      "id": "14065629097",
      "author": "MT-10010",
      "title": "Instant",
      "body": "Instant sucks - needs to be removed",
      "score": 1,
      "updatedAt": "2026-05-14T19:27:16-07:00",
      "deletedAt": null
    },
    {
      "appId": "389801252",
      "id": "14065624583",
      "author": "extrayams",
      "title": "great app, but get back to photography",
      "body": "read that again",
      "score": 5,
      "updatedAt": "2026-05-14T19:25:24-07:00",
      "deletedAt": null
    },
    {
      "appId": "389801252",
      "id": "14065616568",
      "author": "Sql Dude",
      "title": "always gets worse with updates🤣",
      "body": "on this episode. instagram has added ads that completely take over the comment section.\n\nlowered the rating after the instants update dropped. terrible feature and annoying notifications.",
      "score": 1,
      "updatedAt": "2026-05-14T19:21:53-07:00",
      "deletedAt": null
    },
    {
      "appId": "389801252",
      "id": "14065616115",
      "author": "bvtrz",
      "title": "EW INSTANTS?.",
      "body": "Get this feature off my insta.",
      "score": 1,
      "updatedAt": "2026-05-14T19:21:42-07:00",
      "deletedAt": null
    },
    {
      "appId": "389801252",
      "id": "14065578361",
      "author": "Destino0201",
      "title": "The Best App Ever",
      "body": "THE BEST APP EVER for all your Personal & Business needs!!!!",
      "score": 5,
      "updatedAt": "2026-05-14T19:05:17-07:00",
      "deletedAt": null
    },
    {
      "appId": "389801252",
      "id": "14065576438",
      "author": "da og kid",
      "title": "this app used to be good",
      "body": "My main Instagram account got disabled and now every time I try creating a new account they get automatically disabled. Now I have this account that hasn't been disabled but every time I try following one of my friends it would either not show their Instagram account or it would not let me follow it so fix your app and stop all the AI slop. I'm also not able to follow friends that are mutuals with other people I know and once Instagram lets me follow them they don't let me see any new account doesn't matter if I already followed them or if I blocked them it still shows up",
      "score": 1,
      "updatedAt": "2026-05-14T19:04:28-07:00",
      "deletedAt": null
    },
    {
      "appId": "389801252",
      "id": "14065565454",
      "author": "Davidsgoliath",
      "title": "My thoughts",
      "body": "Instagram is good but i don’t get any updates, i check instagram for updates and restart my phone and there still isn’t a updated version of instagram",
      "score": 4,
      "updatedAt": "2026-05-14T18:59:45-07:00",
      "deletedAt": null
    }
  ],
  "447188370": [
    {
      "appId": "447188370",
      "id": "14068419603",
      "author": "levgatz",
      "title": "Riddled with Ads",
      "body": "I have had this app since 2014. Now they want you to pay to avoid the ads that they decided to include. They make their ads seem like you have a message and they give you a notification. Borderline unusable.",
      "score": 1,
      "updatedAt": "2026-05-15T13:14:30-07:00",
      "deletedAt": null
    },
    {
      "appId": "447188370",
      "id": "14068396955",
      "author": "gyrne",
      "title": "DIRECTOR MODE",
      "body": "I Want my director mode back please 🙏",
      "score": 5,
      "updatedAt": "2026-05-15T13:05:57-07:00",
      "deletedAt": null
    },
    {
      "appId": "447188370",
      "id": "14068359064",
      "author": "Julianthegoer",
      "title": "Got banned for no reason",
      "body": "I didnt do anything and i got device banned",
      "score": 1,
      "updatedAt": "2026-05-15T12:51:51-07:00",
      "deletedAt": null
    },
    {
      "appId": "447188370",
      "id": "14068077210",
      "author": "YOURDADDYFRRR",
      "title": "I love it",
      "body": "That I can text all of my friends and funny stuff on here you also get to call and snap each other like saying “what are you doing” or like “where you at” like I’m loving it right now 😍😁",
      "score": 5,
      "updatedAt": "2026-05-15T11:10:16-07:00",
      "deletedAt": null
    },
    {
      "appId": "447188370",
      "id": "14068031170",
      "author": "TayBug05",
      "title": "a video i took vanished.",
      "body": "fix your bs. I saved a video of my daughter just for it to vanish but yall saved the same one twice ?",
      "score": 1,
      "updatedAt": "2026-05-15T10:54:19-07:00",
      "deletedAt": null
    },
    {
      "appId": "447188370",
      "id": "14067833685",
      "author": "suh muh buh",
      "title": "suh muh buh",
      "body": "suh muh buh",
      "score": 5,
      "updatedAt": "2026-05-15T09:48:22-07:00",
      "deletedAt": null
    },
    {
      "appId": "447188370",
      "id": "14067734990",
      "author": "C10110",
      "title": "Banned Without Reason",
      "body": "I have been repeatedly flagged for violating sexual content warnings. I post music i make or little game projects Im working on ffs. I don’t know of someone is harassing me with false reports or what but snap offers zero assistance and has locked the account. \n\nI have been a user for years. I found it really helpful when I don’t want to give my personal cell or socials out but want to “post” mkre like socials. \n\nWell that’s over with lol. I guess it’s fine for Sophie Rain to have her ahh jiggle barely covered and for minors like Piper to be in skimpy bikinis soft launching for OF when they turn 18, but god forbid some guy wants to share a lyric video of an indie folk song he made using gameplay footage from a little top down space game he’s working on as a bg visual. \n\nThey must protect the platform from monsters like me.",
      "score": 1,
      "updatedAt": "2026-05-15T09:16:43-07:00",
      "deletedAt": null
    },
    {
      "appId": "447188370",
      "id": "14067699962",
      "author": "Were she",
      "title": "The best",
      "body": "Very good and has a lot of good stuff to offer",
      "score": 5,
      "updatedAt": "2026-05-15T09:05:40-07:00",
      "deletedAt": null
    },
    {
      "appId": "447188370",
      "id": "14067692505",
      "author": "tiktok_the_god_.",
      "title": "Not good any more",
      "body": "It used to be free and now it’s not and shows a lot of inappropriate thing not worth it",
      "score": 1,
      "updatedAt": "2026-05-15T09:03:21-07:00",
      "deletedAt": null
    },
    {
      "appId": "447188370",
      "id": "14067662766",
      "author": "Gracie_F7",
      "title": "LOVE snap, but hoping for more voiceover accessibility",
      "body": "i love snap, i use it ALL the time. i'm blind and am a voiceover user. even tho snap has gotten way more accessible with the screen reader (thank you!!) i would appreciate even more accessibility. i would love to see the story creation screen with all of the filters/lenses be in a cleaner, more organized layout. i would also appreciate for stickers etc to have proper labeled buttons. it would be cool if the in app camera could help blind ppl with framing when trying to take a pic or vid when a screen reader is enabled so the phone cam doesn't have to be sued as often. it would also be great if it was easier to upload pics/screenshots from camera roll to add captions and then post. also, i have to take screenshots of ppl's stories to see what they are and after i get the description and go back to reply, the reply button no longer shows up. but it's there before i take the screenshot. that just changed very recently unfortunately\nthank you so much for taking the time to read my review and i hope you will consider ways to make the app more accessible/inclusive for blind users!",
      "score": 4,
      "updatedAt": "2026-05-15T08:54:06-07:00",
      "deletedAt": null
    },
    {
      "appId": "447188370",
      "id": "14067550186",
      "author": "Dj unospira",
      "title": "Snapchat",
      "body": "⭐️⭐️⭐️⭐️⭐️it deserve Much more we all loved it",
      "score": 5,
      "updatedAt": "2026-05-15T08:19:54-07:00",
      "deletedAt": null
    },
    {
      "appId": "447188370",
      "id": "14067547245",
      "author": "cxssvii",
      "title": "Lack of Support and Wrongful Perma Ban to Account/Device",
      "body": "One thing about me is i’ve used snap since i was in 5th grade. 2013. i have never gotten a warning, violated guidelines, or anything. Yet somehow about a month ago snap decided to ban me and my account for what they said was me violating their drug policy…i didn’t. apparently it is ALL AI and it can flag you if it senses slang it THINKS is related to said “violated policy” and it’s funny cause they normally don’t even tell you why. so the fact i know i didn’t do that and was also being harassed by someone in real life and online and i tried to explain the matter yet again. another AI reviews the appeal. With this being said and how deep it actually goes as i have even sent a pre arbitration notice that i know they’ll ignore since you cannot file a class-action lawsuit against them per their terms and conditions. it is impossible to get a human to respond and once i try to explain the issue it goes back to AI. i have never actually seen a SERVICE violate their own terms and agreements. yes they can ban you for whatever they want at their will. but to not even have due process and meaningful human review is ridiculous at this point with how long snapchat has been around. could actually give jobs to people who would be willing to do it even. so to do the absolute most to me when i KNOW i was reported by someone trying to mess with my life knowing i had EVERY memory from 6th grade to my first daughter and even up to the point they WRONGFULLY banned me and refuse to even acknowledge an email and DO something to help me while i KNOW the person who did this to mess with me posts the exact violation they said i broke and WORSE. DO NOT download this app thinking you can save pics either cause they’ll probably do this to you too and they want you to pay to have ur own memories anyway. snapchat has become a money hungry greedy service who only gives a chance to those already famous with a following and money and funding it with snapchat+ or SOMETHING cause i almost wonder if this is a common thing to happen to users without snap+ as anyone ik w snap+ gets away with any and everything while those of us not paying and doing nothing wrong get banned…seen it happen time and time again with people close to me. get it together snap. i haven’t been a loyal user for 13 years to not even be able to have a meaningful review and discussion regarding my account especially when snapchat was an avenue to advertise my business and make me money. so now since losing the app also i have lost access to people who buy my good and services as well as a place to market.",
      "score": 1,
      "updatedAt": "2026-05-15T08:19:01-07:00",
      "deletedAt": null
    },
    {
      "appId": "447188370",
      "id": "14067521017",
      "author": "$weeee",
      "title": "Device",
      "body": "They banned me for no reason it won’t ban me. I am device band.",
      "score": 2,
      "updatedAt": "2026-05-15T08:11:14-07:00",
      "deletedAt": null
    },
    {
      "appId": "447188370",
      "id": "14067511796",
      "author": "Knower11",
      "title": "Getting worse all the time",
      "body": "STOP OPENING ON FRONT CAMERA. STOP FLOODING MY PAGE AND STORIES WITH SOFTCORE PORN. It is more bloated each and every day with garbage and ads",
      "score": 1,
      "updatedAt": "2026-05-15T08:08:28-07:00",
      "deletedAt": null
    },
    {
      "appId": "447188370",
      "id": "14067430840",
      "author": "Old Gree",
      "title": "Experience",
      "body": "I’ve used Snapchat off and on over the years and made multiple accounts. Never had any problems. Thank you",
      "score": 5,
      "updatedAt": "2026-05-15T07:44:25-07:00",
      "deletedAt": null
    },
    {
      "appId": "447188370",
      "id": "14067383394",
      "author": "snaphater___1",
      "title": "Terrible",
      "body": "I’d rather delete the app than pay them in order to keep memories. Stupidest idea ever and definitely the downfall of people using this app. Idiots",
      "score": 1,
      "updatedAt": "2026-05-15T07:30:16-07:00",
      "deletedAt": null
    },
    {
      "appId": "447188370",
      "id": "14067331501",
      "author": "جيدامرة",
      "title": "سناب جدا جميل واصور فيه يومياتي وفلتر ومرا حلوة ومافي اي خطر في برنامج👌",
      "body": "اختكم من ليبيا",
      "score": 5,
      "updatedAt": "2026-05-15T07:14:52-07:00",
      "deletedAt": null
    },
    {
      "appId": "447188370",
      "id": "14067236520",
      "author": "ashdoy12",
      "title": "Bans account for no reason",
      "body": "The worse app ever.",
      "score": 1,
      "updatedAt": "2026-05-15T06:46:19-07:00",
      "deletedAt": null
    },
    {
      "appId": "447188370",
      "id": "14066885957",
      "author": "Hiuuiuoooo",
      "title": "Ban this app",
      "body": "This app will ban u for no reason orjust because you report people in the app and ban you for it and then Snapchat will allow minor sexual activity also on this app!!!  so I will be reporting them on the apple and google play store for illegal activity that I have proof of and showing them too",
      "score": 1,
      "updatedAt": "2026-05-15T04:56:03-07:00",
      "deletedAt": null
    },
    {
      "appId": "447188370",
      "id": "14066836380",
      "author": "Bannnn snapcjat",
      "title": "Me snap",
      "body": "Me snapchat device bann ss06 geni_zela1",
      "score": 1,
      "updatedAt": "2026-05-15T04:39:01-07:00",
      "deletedAt": null
    },
    {
      "appId": "447188370",
      "id": "14066601675",
      "author": "Sark0599",
      "title": "Banned",
      "body": "Device",
      "score": 5,
      "updatedAt": "2026-05-15T03:11:17-07:00",
      "deletedAt": null
    },
    {
      "appId": "447188370",
      "id": "14066425577",
      "author": "Ta 🩸 Ha",
      "title": "العراق",
      "body": "بغداد",
      "score": 5,
      "updatedAt": "2026-05-15T01:54:09-07:00",
      "deletedAt": null
    },
    {
      "appId": "447188370",
      "id": "14066352904",
      "author": "Cayden03",
      "title": "Snap",
      "body": "Why the heck do they think it’s ok to make us pay to keep our memories saved?",
      "score": 1,
      "updatedAt": "2026-05-15T01:19:58-07:00",
      "deletedAt": null
    },
    {
      "appId": "447188370",
      "id": "14066187271",
      "author": "67lonelykid67",
      "title": "Public profile",
      "body": "Hello so I love Snapchat but I don’t know how to make a public profile picture",
      "score": 5,
      "updatedAt": "2026-05-15T00:00:38-07:00",
      "deletedAt": null
    },
    {
      "appId": "447188370",
      "id": "14065923130",
      "author": "!,8:929¥.¥",
      "title": "Disable automatic music!",
      "body": "There isn’t an option to disable automatic music sound when taking a video, it’s very high-pitched and alarming when you try to remove it!",
      "score": 1,
      "updatedAt": "2026-05-14T21:47:27-07:00",
      "deletedAt": null
    },
    {
      "appId": "447188370",
      "id": "14065872233",
      "author": "@mr.kaddar",
      "title": "كثير الاعلانات",
      "body": "سيى",
      "score": 2,
      "updatedAt": "2026-05-14T21:21:56-07:00",
      "deletedAt": null
    },
    {
      "appId": "447188370",
      "id": "14065730854",
      "author": "Sabrina Hayes",
      "title": "Chats duration settings",
      "body": "Chats set to never and snaps saved in chat for 24 hours don’t stay in once swiped out of chat and swiped back in it disappears …",
      "score": 3,
      "updatedAt": "2026-05-14T20:13:39-07:00",
      "deletedAt": "2026-05-17T03:24:27.162Z"
    },
    {
      "appId": "447188370",
      "id": "14065591507",
      "author": "papo is taken",
      "title": "This app sucks",
      "body": "I lost everything. I heard about them deleting memories so they can charge you for that but losing stuff from “My Eyes Only” was not what I was expecting. I absolutely lost everything in there since 2017 everything gone. Disappeared from the face of the earth I want to delete this app so bad this app sucks",
      "score": 1,
      "updatedAt": "2026-05-14T19:11:00-07:00",
      "deletedAt": "2026-05-17T03:24:27.162Z"
    },
    {
      "appId": "447188370",
      "id": "14065578383",
      "author": "Gamenameooo",
      "title": "Khdijdb",
      "body": "Kebdoj a",
      "score": 5,
      "updatedAt": "2026-05-14T19:05:18-07:00",
      "deletedAt": "2026-05-17T03:24:27.162Z"
    },
    {
      "appId": "447188370",
      "id": "14065545937",
      "author": "Dare vocie changer",
      "title": "NEW STORAGE UPDATE",
      "body": "I find it absolutely crazy that snapchat is now forcing you to PAY TO KEEEP YOIR MEMORIES! it’s absolutely insane, that an app that has gone so long without charging is now starting too, Btw i was one of the first people who subscribes to snap + and not even premium member get free storage, i understand paying for things that are optional like festines but memories are just out of the question, that’s kinda the whole point to why ppl have the app. i dont stand by ts.",
      "score": 1,
      "updatedAt": "2026-05-14T18:51:29-07:00",
      "deletedAt": "2026-05-17T03:24:27.162Z"
    },
    {
      "appId": "447188370",
      "id": "14065533800",
      "author": "Supermom1996",
      "title": "Mad",
      "body": "My snaps are disappearing",
      "score": 1,
      "updatedAt": "2026-05-14T18:46:19-07:00",
      "deletedAt": "2026-05-17T03:24:27.162Z"
    },
    {
      "appId": "447188370",
      "id": "14065529669",
      "author": "Travis fort",
      "title": "Really good",
      "body": "Besides the constant friend requests I get this app is really good for social media marketing and other stuff",
      "score": 4,
      "updatedAt": "2026-05-14T18:44:34-07:00",
      "deletedAt": "2026-05-17T03:24:27.162Z"
    },
    {
      "appId": "447188370",
      "id": "14065525334",
      "author": "Tree Butler",
      "title": "Next level",
      "body": "Love love love",
      "score": 5,
      "updatedAt": "2026-05-14T18:42:44-07:00",
      "deletedAt": "2026-05-17T03:24:27.162Z"
    },
    {
      "appId": "447188370",
      "id": "14065299147",
      "author": "AvaOswald",
      "title": "Best friends",
      "body": "It’s an absolutely amazing app! Although it would be way better if the best friend emojis/labels went past 2 months. Like have it with 5 months, 8 months, 1 year etc. But besides that it’s absolutely wonderful and the filters so fun and making friends",
      "score": 4,
      "updatedAt": "2026-05-14T17:08:42-07:00",
      "deletedAt": "2026-05-17T03:24:27.162Z"
    },
    {
      "appId": "447188370",
      "id": "14065249270",
      "author": "William87734",
      "title": "Like it but need desperate help",
      "body": "I love the app but the notification belll is frozen and unresponsive to clock. Please help and fix this asap",
      "score": 5,
      "updatedAt": "2026-05-14T16:47:29-07:00",
      "deletedAt": "2026-05-17T03:24:27.162Z"
    },
    {
      "appId": "447188370",
      "id": "14065200974",
      "author": "3v3ryone will love it",
      "title": "PLEASE everyone will love this",
      "body": "Please please please add the feature where you can control the other persons screens on call",
      "score": 1,
      "updatedAt": "2026-05-14T16:26:50-07:00",
      "deletedAt": "2026-05-17T03:24:27.162Z"
    },
    {
      "appId": "447188370",
      "id": "14065193552",
      "author": "Mad customer92",
      "title": "Baddddd",
      "body": "Someone was harassing me & ended up reporting me for no reason and then I end up getting banned. It’s ridiculous",
      "score": 1,
      "updatedAt": "2026-05-14T16:23:42-07:00",
      "deletedAt": "2026-05-17T03:24:27.162Z"
    },
    {
      "appId": "447188370",
      "id": "14065183436",
      "author": "Yaqchat",
      "title": "Snap Plus +",
      "body": "Great with snap +",
      "score": 4,
      "updatedAt": "2026-05-14T16:19:20-07:00",
      "deletedAt": "2026-05-17T03:24:27.162Z"
    },
    {
      "appId": "447188370",
      "id": "14064972323",
      "author": "RebekahCia",
      "title": "I love Snapchat",
      "body": "I like it it’s pretty call an fun",
      "score": 5,
      "updatedAt": "2026-05-14T14:50:58-07:00",
      "deletedAt": "2026-05-17T03:24:27.162Z"
    },
    {
      "appId": "447188370",
      "id": "14064889750",
      "author": "Esthetic app",
      "title": "Snap",
      "body": "I like it is like instant and more things",
      "score": 5,
      "updatedAt": "2026-05-14T14:17:33-07:00",
      "deletedAt": "2026-05-17T03:24:27.162Z"
    },
    {
      "appId": "447188370",
      "id": "14064822420",
      "author": "What am DM",
      "title": "Banned",
      "body": "I got banned for being falsely reported",
      "score": 2,
      "updatedAt": "2026-05-14T13:50:50-07:00",
      "deletedAt": "2026-05-17T03:24:27.162Z"
    },
    {
      "appId": "447188370",
      "id": "14064725904",
      "author": "Spudy100",
      "title": "Snappin",
      "body": "I love the seemingly endless filters and audio combinations that keep me snappin away. Love my streaks with my friends and the memories saved in my snaps!",
      "score": 3,
      "updatedAt": "2026-05-14T13:13:21-07:00",
      "deletedAt": "2026-05-17T03:24:27.162Z"
    },
    {
      "appId": "447188370",
      "id": "14064689921",
      "author": "boguy0227",
      "title": "Idk",
      "body": "I can talk to friends",
      "score": 5,
      "updatedAt": "2026-05-14T12:59:27-07:00",
      "deletedAt": "2026-05-17T03:24:27.162Z"
    },
    {
      "appId": "447188370",
      "id": "14064639742",
      "author": "Yordle94",
      "title": "My personal feed back",
      "body": "Yesss it’s Snapchat YESSSS ITS GREAT we all love it, but as a paying member for “premium” I don’t appreciate the adds after every individual friends story I’m watching! I understand some adds here and there but 50% of my snap screen time is literally ADDS! It’s beyond annoying! I’d I’ve it 4 stars if it was not for the excessive adds! Over all like come on its SNAPCHAT ofc it’s great!",
      "score": 3,
      "updatedAt": "2026-05-14T12:40:23-07:00",
      "deletedAt": "2026-05-17T03:24:27.162Z"
    },
    {
      "appId": "447188370",
      "id": "14064524813",
      "author": "Lover6542",
      "title": "Shouldn't have to pay for storage when it's been free for years",
      "body": "Change the fees",
      "score": 2,
      "updatedAt": "2026-05-14T11:57:53-07:00",
      "deletedAt": "2026-05-17T03:24:27.162Z"
    },
    {
      "appId": "447188370",
      "id": "14064482116",
      "author": "tpic123",
      "title": "memories",
      "body": "memories were the best part of snapchat, now they are making us pay for it or deleting everything this is absurd",
      "score": 1,
      "updatedAt": "2026-05-14T11:42:19-07:00",
      "deletedAt": "2026-05-17T03:24:27.162Z"
    },
    {
      "appId": "447188370",
      "id": "14064206016",
      "author": "Fathi2002",
      "title": "The best",
      "body": "Snapchat is the best I downloaded Snapchat in 2020 and I haven’t stopped. I have WhatsApp and still type in Snapchat and call Snapchat. I don’t know why I recommend to download Snapchat. It’s literally the best like you can still send voice messages without even having Internet I’m 21 and I don’t know how I like. Discover Snapchat in 2020? but still to this day, I still use it.",
      "score": 5,
      "updatedAt": "2026-05-14T10:05:38-07:00",
      "deletedAt": "2026-05-17T03:24:27.162Z"
    },
    {
      "appId": "447188370",
      "id": "14064185087",
      "author": "Dyako2013",
      "title": "Nice app ever",
      "body": "Nice app ever",
      "score": 5,
      "updatedAt": "2026-05-14T09:58:32-07:00",
      "deletedAt": "2026-05-17T03:24:27.162Z"
    },
    {
      "appId": "447188370",
      "id": "14064182495",
      "author": "1342359",
      "title": "Used to be better",
      "body": "You gotta pay for ad block they don’t let you block team Snapchat anymore nobody uses this since that update terrible app",
      "score": 1,
      "updatedAt": "2026-05-14T09:57:39-07:00",
      "deletedAt": "2026-05-17T03:24:27.162Z"
    },
    {
      "appId": "447188370",
      "id": "14064110620",
      "author": "goddess gc",
      "title": "Update",
      "body": "Snapchat Is a great and nice app easy to use. Snapchat Should start going live stream. It's a easy fun way of making money through the app, through Gifts, The app will gain from it. it's another way of generating money from the live streams to. Users can buy. coins from the app.",
      "score": 4,
      "updatedAt": "2026-05-14T09:33:46-07:00",
      "deletedAt": "2026-05-17T03:24:27.162Z"
    },
    {
      "appId": "447188370",
      "id": "14069094268",
      "author": "wald. ancja",
      "title": "Snap memories",
      "body": "why do i have to pay to save memories in the app when that’s the whole purpose of the app probably just gonna delete the app now and save them to camera roll",
      "score": 1,
      "updatedAt": "2026-05-15T17:45:45-07:00",
      "deletedAt": null
    },
    {
      "appId": "447188370",
      "id": "14068957700",
      "author": "Relexify",
      "title": "Tilly",
      "body": "Sigma",
      "score": 5,
      "updatedAt": "2026-05-15T16:51:05-07:00",
      "deletedAt": null
    },
    {
      "appId": "447188370",
      "id": "14068894176",
      "author": "Almutiriiiiiiiiiii",
      "title": "Rehab",
      "body": "🌟🌟🌟🌟🌟🌟🌟🌟🌟🌟🌟🌟🌟🌟🌟🌟🌟🌟🌟🌟🌟🌟🌟🌟🌟🌟🌟🌟🌟🌟",
      "score": 5,
      "updatedAt": "2026-05-15T16:24:47-07:00",
      "deletedAt": null
    },
    {
      "appId": "447188370",
      "id": "14068868440",
      "author": "ارجوان كمال",
      "title": "شنكال",
      "body": "ارجو",
      "score": 5,
      "updatedAt": "2026-05-15T16:14:15-07:00",
      "deletedAt": null
    },
    {
      "appId": "447188370",
      "id": "14068772076",
      "author": "(3&28:!!3",
      "title": "Ads?!",
      "body": "I don’t mind the ads between each Snapchat story or during Snapchat stories, but to have ads on my messaging feed when I literally pay for Snapchat plus I should not have ads in my chat feed. It’s annoying. And if someone’s paying for Snapchat, plus they shouldn’t have ads. Not that hard to comprehend.",
      "score": 1,
      "updatedAt": "2026-05-15T15:34:28-07:00",
      "deletedAt": null
    },
    {
      "appId": "447188370",
      "id": "14068628097",
      "author": "Sigma Judd",
      "title": "Really good app",
      "body": "Tuff",
      "score": 5,
      "updatedAt": "2026-05-15T14:35:47-07:00",
      "deletedAt": null
    },
    {
      "appId": "447188370",
      "id": "14068625324",
      "author": "Maria’s⭐️✨🌟🤩",
      "title": "Reposts go to stories",
      "body": "I love this app but I hate how when I repost it goes to my story because what if I want my reposts to be private? It’s honestly kinda annoying and I think u should make the option if u wanna post it on the story my instead of it automatically doing it",
      "score": 4,
      "updatedAt": "2026-05-15T14:34:38-07:00",
      "deletedAt": null
    }
  ],
  "595068606": [
    {
      "appId": "595068606",
      "id": "14066544194",
      "author": "SVA_SVA",
      "title": "Toggle Option",
      "body": "Very nice app! So convenient when having to split checks. A toggle option to view the picture of the receipt while making edits would be nice.",
      "score": 5,
      "updatedAt": "2026-05-15T02:47:10-07:00",
      "deletedAt": null
    },
    {
      "appId": "595068606",
      "id": "14059691123",
      "author": "LocalTraveler",
      "title": "Used to be good, much better options available these days",
      "body": "For many years, this was my go to app to split the dinner bill. It wasn’t always perfect, but it was the best available at the time. It’s pretty frustrating when it gets it wrong though, because when you’re at dinner with a large group of friends…trying to figure it out, there’s a lot of pressure and it just gets confusing not knowing which price it got wrong.\n\nThankfully, tech has improved, and now I can’t live without “fairShare - split the bill”.   It has all the bells and whistles and features you could want while still keeping the UI simple and clean. Best part is it’s always accurate and all my friends can pick their own items without downloading the app or needing a login. Easy Peezy.",
      "score": 2,
      "updatedAt": "2026-05-13T05:30:17-07:00",
      "deletedAt": "2026-05-17T03:24:32.322Z"
    },
    {
      "appId": "595068606",
      "id": "14042000396",
      "author": "Docular123",
      "title": "Rarely works",
      "body": "It only works sometimes and it’s so frustrating. You would think we have better technology by now",
      "score": 2,
      "updatedAt": "2026-05-08T08:48:20-07:00",
      "deletedAt": "2026-05-17T03:24:32.322Z"
    },
    {
      "appId": "595068606",
      "id": "14019035448",
      "author": "David C Tran",
      "title": "Great.  Missing Zelle",
      "body": "Really like this app. Great for groups. Would love for more payment options. Zelle maybe?",
      "score": 4,
      "updatedAt": "2026-05-01T23:21:46-07:00",
      "deletedAt": "2026-05-17T03:24:32.322Z"
    },
    {
      "appId": "595068606",
      "id": "13947539904",
      "author": "Nserrano1999",
      "title": "Almost perfect",
      "body": "This app would be perfect if each user splitting the bill had a different color assigned. That way it would be easier to track which line items have been assigned to each user. For share items the line could have multiple colors.",
      "score": 4,
      "updatedAt": "2026-04-11T12:17:31-07:00",
      "deletedAt": "2026-05-17T03:24:32.322Z"
    },
    {
      "appId": "595068606",
      "id": "13935642583",
      "author": "Assassinfkfndba",
      "title": "10/10",
      "body": "Works so well idk how it’s free",
      "score": 5,
      "updatedAt": "2026-04-08T06:03:17-07:00",
      "deletedAt": "2026-05-17T03:24:32.322Z"
    },
    {
      "appId": "595068606",
      "id": "13927056210",
      "author": "AdamGramling",
      "title": "Cannot upload images",
      "body": "Missing the most basic feature… you can only use if you take a photo of the receipt. You cannot upload a previous photo",
      "score": 2,
      "updatedAt": "2026-04-05T18:21:45-07:00",
      "deletedAt": "2026-05-17T03:24:32.322Z"
    },
    {
      "appId": "595068606",
      "id": "13926747779",
      "author": "Jhmph",
      "title": "Tax input not working",
      "body": "The app works great except for the fact that the tax button is broken and you cannot calculate the correct amount",
      "score": 1,
      "updatedAt": "2026-04-05T16:05:13-07:00",
      "deletedAt": "2026-05-17T03:24:32.322Z"
    },
    {
      "appId": "595068606",
      "id": "13924306823",
      "author": "The Arthurian Legend",
      "title": "Great app",
      "body": "Used this for years. Just a simple yet great tool",
      "score": 5,
      "updatedAt": "2026-04-05T00:25:59-07:00",
      "deletedAt": "2026-05-17T03:24:32.322Z"
    },
    {
      "appId": "595068606",
      "id": "13922518783",
      "author": "Jazabby",
      "title": "Not really simpler",
      "body": "Does what its supposed to, but frustrating to have to manage automatic tip addition each time I use it. Not all expenses are tip-able.",
      "score": 2,
      "updatedAt": "2026-04-04T11:28:28-07:00",
      "deletedAt": "2026-05-17T03:24:32.322Z"
    },
    {
      "appId": "595068606",
      "id": "13915321101",
      "author": "Natbeans",
      "title": "SO unintuitive",
      "body": "it’s truly as if this app was built to\nbe difficult to use. it’s horrible at scanning a picture of a receipt. you have to enter in manually and it takes ages. the bills auto delete after just a couple of weeks.",
      "score": 1,
      "updatedAt": "2026-04-02T12:22:41-07:00",
      "deletedAt": "2026-05-17T03:24:32.322Z"
    },
    {
      "appId": "595068606",
      "id": "13901206841",
      "author": "Sirpingalot",
      "title": "Great for splitting tabs",
      "body": "Always a problem with restaurants not splitting it into too many cheques. But this app makes it a breeze. Scans your receipt so you don’t have to hand type everything and lets you pick what you ate. I’ve never tried the bank integration but splitting the bill has definitely become less of a hassle. Totally recommend if you are usually in groups that need it split.",
      "score": 4,
      "updatedAt": "2026-03-29T13:47:11-07:00",
      "deletedAt": "2026-05-17T03:24:32.322Z"
    },
    {
      "appId": "595068606",
      "id": "13878499389",
      "author": "ritamedina",
      "title": "Font",
      "body": "Excellent app! Sometimes I have issues downloading the info cause it doesn’t recognize some fonts.",
      "score": 5,
      "updatedAt": "2026-03-23T06:25:13-07:00",
      "deletedAt": "2026-05-17T03:24:32.322Z"
    },
    {
      "appId": "595068606",
      "id": "13866758017",
      "author": "ric_risnc",
      "title": "Tab",
      "body": "Great app",
      "score": 5,
      "updatedAt": "2026-03-19T21:10:40-07:00",
      "deletedAt": "2026-05-17T03:24:32.322Z"
    },
    {
      "appId": "595068606",
      "id": "13832709966",
      "author": "aprauhl18",
      "title": "Discounts Incorrect",
      "body": "There needs to be an option to add a percentage as a discount and not just the total of the discount itself. It’s not calculating each persons total correct because it’s splitting the discount with everyone. How would it know where the $120 discount came from? When everyone received 20% off the bill? When I do the math myself it’s not splitting or calculating correctly. The option to add a discount on the bill as a “percentage” would be very helpful. \n\nSame thing with adding tax. I should be able to insert the tax percentage like I can with tip instead of only being able to add the amount manually.",
      "score": 1,
      "updatedAt": "2026-03-10T00:31:47-07:00",
      "deletedAt": "2026-05-17T03:24:32.322Z"
    },
    {
      "appId": "595068606",
      "id": "13831372774",
      "author": "Stephen Kirby",
      "title": "Great app",
      "body": "Efficient and effective",
      "score": 5,
      "updatedAt": "2026-03-09T13:56:52-07:00",
      "deletedAt": "2026-05-17T03:24:32.322Z"
    },
    {
      "appId": "595068606",
      "id": "13802558009",
      "author": "JannaH16",
      "title": "Game changer!",
      "body": "Using this app on a girl’s trip made splitting the costs so easy! Unlike most similar apps, I was able to split the tabs easily, without everyone having to have an account or join the bill to claim their items. 10/10 recommend!",
      "score": 5,
      "updatedAt": "2026-03-01T07:01:46-07:00",
      "deletedAt": "2026-05-17T03:24:32.322Z"
    },
    {
      "appId": "595068606",
      "id": "13764272604",
      "author": "Jd4574446777",
      "title": "Let me upload images",
      "body": "Took a photo last night of a receipt. I want to use that image 🤷🏻‍♂️",
      "score": 1,
      "updatedAt": "2026-02-18T16:00:35-07:00",
      "deletedAt": "2026-05-17T03:24:32.322Z"
    },
    {
      "appId": "595068606",
      "id": "13675700117",
      "author": "Capt. Lionel Mandrake",
      "title": "Used to work better",
      "body": "I’ve had this app forever and known the workarounds well but the last 3-4, admittedly infrequent uses, it’s failed horribly. Dropping items, tax, or adding something that isn’t a menu item.",
      "score": 3,
      "updatedAt": "2026-01-25T14:34:24-07:00",
      "deletedAt": "2026-05-17T03:24:32.322Z"
    },
    {
      "appId": "595068606",
      "id": "13655694120",
      "author": "Emzy14",
      "title": "Used and loved for years",
      "body": "It is so helpful for splitting checks! One of my favorite apps.",
      "score": 5,
      "updatedAt": "2026-01-20T07:28:15-07:00",
      "deletedAt": "2026-05-17T03:24:32.322Z"
    },
    {
      "appId": "595068606",
      "id": "13650622080",
      "author": "Bel_8675309",
      "title": "I love this app!",
      "body": "I love this app sooo much. I’ve been using it for years and it’s such a huge help when you dine out with friends/people and you want to split the tab evenly. You might have to manually input things once in a while when the camera can’t get the whole receipt but other than that it’s a great app!",
      "score": 5,
      "updatedAt": "2026-01-18T22:55:29-07:00",
      "deletedAt": "2026-05-17T03:24:32.322Z"
    },
    {
      "appId": "595068606",
      "id": "13584602004",
      "author": "Romance_geek",
      "title": "Best App",
      "body": "I use the app frequently with friends and it never fails!",
      "score": 5,
      "updatedAt": "2026-01-02T02:18:06-07:00",
      "deletedAt": "2026-05-17T03:24:32.322Z"
    },
    {
      "appId": "595068606",
      "id": "13582760986",
      "author": "JoMaMa Rocks!",
      "title": "Tips SUCK",
      "body": "Horrible! Mandatory tip calculations SUCK!",
      "score": 1,
      "updatedAt": "2026-01-01T14:55:11-07:00",
      "deletedAt": "2026-05-17T03:24:32.322Z"
    },
    {
      "appId": "595068606",
      "id": "13571224909",
      "author": "Alex Dinnouti",
      "title": "A Must-Have for Group Dining",
      "body": "Great app with a clear mission, a simple interface, and excellent usability. It does exactly what it needs to do.\n\nThe app accurately scans most receipts and includes an editor for the few that need manual adjustments.\n\nYou can pass your phone around so everyone can tag their items, or share a code for friends who already have the app.\n\nThere’s also a birthday feature that lets you easily include or exclude the birthday person when splitting the bill.",
      "score": 5,
      "updatedAt": "2025-12-29T18:31:07-07:00",
      "deletedAt": "2026-05-17T03:24:32.322Z"
    },
    {
      "appId": "595068606",
      "id": "13540082546",
      "author": "Dg-000",
      "title": "Not accurate",
      "body": "The app is convenient at times but not very accurate. I’ve tried to use it plenty of times with well lit and clear pictures and the numbers it pulls is crazy sometimes…not really worth it",
      "score": 1,
      "updatedAt": "2025-12-21T13:23:26-07:00",
      "deletedAt": "2026-05-17T03:24:32.322Z"
    },
    {
      "appId": "595068606",
      "id": "13519101469",
      "author": "Carlosgjm",
      "title": "Great simple app",
      "body": "Lifesaver app for going to dinner with friends. Simple UI and makes it easy to use. No problems making the checks split. Venmo integration is buggy but screenshotting works fine. Highly recommend!",
      "score": 5,
      "updatedAt": "2025-12-15T22:23:04-07:00",
      "deletedAt": "2026-05-17T03:24:32.322Z"
    },
    {
      "appId": "595068606",
      "id": "13515479923",
      "author": "SoCal Kman",
      "title": "It works!",
      "body": "With all the eating with different families and sports team, Tab is super easy to use. I took a picture of the receipt and it OCR and created a receipt in the app that I can just click line items. It auto added tax and I can adjust the tip amount. So easy!",
      "score": 5,
      "updatedAt": "2025-12-14T22:46:45-07:00",
      "deletedAt": "2026-05-17T03:24:32.322Z"
    },
    {
      "appId": "595068606",
      "id": "13471185817",
      "author": "Fishy Fishy bubbles",
      "title": "Good but glitchy",
      "body": "It’s an awesome tool when it works. The issue is it doesn’t work half the time. It will often record the date or time on the receipt as a price and throw everything off. Or sometimes it won’t scan or read items randomly in the middle of the bill. Sometimes I have to scan receipts two or three times before it starts to work.",
      "score": 3,
      "updatedAt": "2025-12-03T10:30:13-07:00",
      "deletedAt": "2026-05-17T03:24:32.322Z"
    },
    {
      "appId": "595068606",
      "id": "13441472819",
      "author": "ekrasno",
      "title": "Ok",
      "body": "Works ok. Pretty difficult to navigate at first and still difficult after you figure out how it works. Not very intuitive. Can’t edit bills after 1 week.",
      "score": 2,
      "updatedAt": "2025-11-25T18:07:40-07:00",
      "deletedAt": "2026-05-17T03:24:32.322Z"
    },
    {
      "appId": "595068606",
      "id": "13355521334",
      "author": "Jes-NYC",
      "title": "Tax, Venmo",
      "body": "There’s no ability to add tax manually, venmo doesn’t connect",
      "score": 2,
      "updatedAt": "2025-11-04T06:11:05-07:00",
      "deletedAt": "2026-05-17T03:24:32.322Z"
    },
    {
      "appId": "595068606",
      "id": "13288857940",
      "author": "Bugmeister96",
      "title": "so awesome!",
      "body": "this makes my life so much easier!! honestly i love this\n\nthe only thing i would like is if they wouldn’t do automatic tax \n\nyou can even input your own information for the check! it’s so great",
      "score": 5,
      "updatedAt": "2025-10-19T17:08:22-07:00",
      "deletedAt": "2026-05-17T03:24:32.322Z"
    },
    {
      "appId": "595068606",
      "id": "13254677128",
      "author": "Jackson00000001",
      "title": "Everything I need",
      "body": "How is this not a regular used app?? It’s amazing, adjustable, easy to use and integrates with either in-vivo pictures or pictures I’ve previously taken! I’ve had the “pleasure” of being the guy who calculates what everyone owes me and their tax and tip. This breaks it down into each person’s stuff, lets me add multiple people to the same item, and even divide an item into 3rds, 4ths, or 5ths! It’s awesome, cannot recommend it enough",
      "score": 5,
      "updatedAt": "2025-10-11T17:06:03-07:00",
      "deletedAt": "2026-05-17T03:24:32.322Z"
    },
    {
      "appId": "595068606",
      "id": "13222875040",
      "author": "Littlebrittles",
      "title": "Doesn’t Capture Well",
      "body": "Tried about four times and after the initial photo is taken of the bill, it only captures specific items and omits several others. This app might work if you’re at a restaurant splitting one item, but don’t count on it working for anything else but that.",
      "score": 1,
      "updatedAt": "2025-10-04T07:55:12-07:00",
      "deletedAt": "2026-05-17T03:24:32.322Z"
    },
    {
      "appId": "595068606",
      "id": "13200785510",
      "author": "Mmcnuggy",
      "title": "Game Changer for Groups",
      "body": "Love using this to split the dinner bill with my friends! Makes it so much easier on the wait staff and we don’t worry about getting totals mixed up.",
      "score": 5,
      "updatedAt": "2025-09-29T08:12:34-07:00",
      "deletedAt": "2026-05-17T03:24:32.322Z"
    },
    {
      "appId": "595068606",
      "id": "13165612391",
      "author": "chrisismad223",
      "title": "Just what i needed",
      "body": "simple, makes math and recording easier. no need for all the integration nonsense but venmo could be nice if they got it working.",
      "score": 5,
      "updatedAt": "2025-09-21T05:32:18-07:00",
      "deletedAt": "2026-05-17T03:24:32.322Z"
    },
    {
      "appId": "595068606",
      "id": "13137675727",
      "author": "lavendergoyl",
      "title": "hallucinating money",
      "body": "the first page of the app works great from scanning the receipt picture, but for some reason on the subtotal page it was adding a ton of money from nowhere to my bill. also can’t connect venmo.",
      "score": 1,
      "updatedAt": "2025-09-14T11:51:04-07:00",
      "deletedAt": "2026-05-17T03:24:32.322Z"
    },
    {
      "appId": "595068606",
      "id": "13117777562",
      "author": "bikthovcsaf",
      "title": "Great App!!",
      "body": "Smooth process and simple interface",
      "score": 5,
      "updatedAt": "2025-09-09T09:21:15-07:00",
      "deletedAt": "2026-05-17T03:24:32.322Z"
    },
    {
      "appId": "595068606",
      "id": "13109453408",
      "author": "Mackenzie Mer",
      "title": "Worst App Ever",
      "body": "Have never used it, when I upload receipt it captured on 2 items off a receipt with 15 items. Second time I tried it added items but didn’t have correct price with each thing. Absolutely horrible, deleting right away",
      "score": 1,
      "updatedAt": "2025-09-07T05:31:43-07:00",
      "deletedAt": "2026-05-17T03:24:32.322Z"
    },
    {
      "appId": "595068606",
      "id": "13103487688",
      "author": "wtfthyarealltaken",
      "title": "Great tool, but needs options",
      "body": "It’s an awesome free tool EXCEPT it factors tip without tax, which is not how most people determine tip. When you select 20% somewhere it’s based on Total to include tax. I’m going to have to look for another tool or hope they add an option.",
      "score": 4,
      "updatedAt": "2025-09-05T16:46:39-07:00",
      "deletedAt": "2026-05-17T03:24:32.322Z"
    },
    {
      "appId": "595068606",
      "id": "13077167092",
      "author": "Cfermorales90",
      "title": "Best tab splitter when out with friends",
      "body": "I love this app! I whip it out every time I’m out with friends and it makes our lives so much easier!",
      "score": 5,
      "updatedAt": "2025-08-29T22:35:23-07:00",
      "deletedAt": "2026-05-17T03:24:32.322Z"
    },
    {
      "appId": "595068606",
      "id": "13077029147",
      "author": "YvesTaty",
      "title": "Terrible",
      "body": "It’s not calculating the bill correctly",
      "score": 1,
      "updatedAt": "2025-08-29T21:33:53-07:00",
      "deletedAt": "2026-05-17T03:24:32.322Z"
    },
    {
      "appId": "595068606",
      "id": "13045751538",
      "author": "jburga29",
      "title": "Tax option not working",
      "body": "I think this app is overall great, but not sure why it doesn’t allow me to change the tax section. I found a loophole to add it as an item but it seems like that’s an issue that needs to resolve.",
      "score": 2,
      "updatedAt": "2025-08-21T21:34:54-07:00",
      "deletedAt": "2026-05-17T03:24:32.322Z"
    },
    {
      "appId": "595068606",
      "id": "13035220214",
      "author": "P414ounce",
      "title": "The best!",
      "body": "Tab has saved so much time and energy splitting the bill with friends. I only wish the Venmo functionality would work. THAT would be totally 5/5 stars.",
      "score": 4,
      "updatedAt": "2025-08-19T05:53:57-07:00",
      "deletedAt": "2026-05-17T03:24:32.322Z"
    },
    {
      "appId": "595068606",
      "id": "13034027149",
      "author": "J25996",
      "title": "love it, just wish it had venmo connection",
      "body": "4/5, would give 5/5 if the venmo connection worked",
      "score": 4,
      "updatedAt": "2025-08-18T22:23:44-07:00",
      "deletedAt": "2026-05-17T03:24:32.322Z"
    },
    {
      "appId": "595068606",
      "id": "12989547253",
      "author": "Adrian...415",
      "title": "One of the best apps but…",
      "body": "It saves sonic headache of having to manually divide up restaurant items buttttt I wish you can connect to Venmo. It has the option but it’s stuck on the Authorizing App screen:/ Besides that, great app",
      "score": 4,
      "updatedAt": "2025-08-07T20:40:53-07:00",
      "deletedAt": "2026-05-17T03:24:32.322Z"
    },
    {
      "appId": "595068606",
      "id": "12971449892",
      "author": "3E-V",
      "title": "Amazing!!",
      "body": "Great app!! You should consider an option for splitting regular receipts like for Costco where it lists out the discounts per item nor just batched discount at the end",
      "score": 5,
      "updatedAt": "2025-08-03T08:50:42-07:00",
      "deletedAt": "2026-05-17T03:24:32.322Z"
    },
    {
      "appId": "595068606",
      "id": "12967765248",
      "author": "Scrumpyfu",
      "title": "App doesn’t connect to Venmo",
      "body": "Lacking that ability makes this app totally useless.",
      "score": 1,
      "updatedAt": "2025-08-02T09:57:06-07:00",
      "deletedAt": "2026-05-17T03:24:32.322Z"
    },
    {
      "appId": "595068606",
      "id": "12888944946",
      "author": "HateTab",
      "title": "Good idea but no functionality",
      "body": "Never able to load Venmo so what’s the point?",
      "score": 1,
      "updatedAt": "2025-07-13T19:16:01-07:00",
      "deletedAt": "2026-05-17T03:24:32.322Z"
    },
    {
      "appId": "595068606",
      "id": "12869938546",
      "author": "TereF88",
      "title": "Super helpful",
      "body": "Great for when going out with friends and splitting the check",
      "score": 5,
      "updatedAt": "2025-07-08T22:31:43-07:00",
      "deletedAt": "2026-05-17T03:24:32.322Z"
    },
    {
      "appId": "595068606",
      "id": "12837699090",
      "author": "Mitchell Motlagh",
      "title": "Great app",
      "body": "Simple and fast. No complaints.",
      "score": 5,
      "updatedAt": "2025-06-30T20:44:50-07:00",
      "deletedAt": "2026-05-17T03:24:32.322Z"
    }
  ],
  "686449807": [
    {
      "appId": "686449807",
      "id": "14067432117",
      "author": "sofya_aga",
      "title": "тг супер",
      "body": "самый лучший мессенджер! удобный,приватный. приятное глазу оформление. много различных полезных функций,которые помогают без проблем коммуницировать с людьми в мессенджере. однозначно топ! 10/10",
      "score": 5,
      "updatedAt": "2026-05-15T07:44:48-07:00",
      "deletedAt": null
    },
    {
      "appId": "686449807",
      "id": "14066333435",
      "author": "kappibare",
      "title": "Голосовые",
      "body": "Сделайте возможность выбрать устройство ввода, чтобы можно было выбрать как записывать ГС. Чтобы при подключенных наушниках можно было использовать микрофон iPhone",
      "score": 4,
      "updatedAt": "2026-05-15T01:10:42-07:00",
      "deletedAt": null
    },
    {
      "appId": "686449807",
      "id": "14066169516",
      "author": "funchozaa",
      "title": "Комментарий",
      "body": "The best messenger! Very convenient, a lot of possibilities 🤍",
      "score": 5,
      "updatedAt": "2026-05-14T23:51:50-07:00",
      "deletedAt": null
    },
    {
      "appId": "686449807",
      "id": "14065488168",
      "author": "erqutj",
      "title": "A good app",
      "body": "The only thing that makes me madly stressed is that unknown people can keep me in touch! And I won't even get a notification that someone saved my account! That is, I can sit and not even know that some person can \"watch\" my account. I think it's scary and not safe, because little can happen. Add at least alerts that someone saved me in contacts 🤔",
      "score": 3,
      "updatedAt": "2026-05-14T18:27:05-07:00",
      "deletedAt": "2026-05-17T03:24:37.625Z"
    },
    {
      "appId": "686449807",
      "id": "14065049068",
      "author": "The BWR",
      "title": "Account frozen",
      "body": "My account was frozen within 2 hours of uploading. Appeals process is a joke. Read up and it happens a lot. I’m not gonna change my number for this app. No stars",
      "score": 1,
      "updatedAt": "2026-05-14T15:22:45-07:00",
      "deletedAt": "2026-05-17T03:24:37.625Z"
    },
    {
      "appId": "686449807",
      "id": "14064273308",
      "author": "BenjaminBalderas",
      "title": "Forces to pay??",
      "body": "Can’t sign in because I have to pay a 1 week fee?? Why",
      "score": 1,
      "updatedAt": "2026-05-14T10:28:32-07:00",
      "deletedAt": "2026-05-17T03:24:37.625Z"
    },
    {
      "appId": "686449807",
      "id": "14064196484",
      "author": "Jt$101",
      "title": "Do not download this",
      "body": "I downloaded this because I got mixed up with messenger and this and come to found out this app is used for cp so don’t download this",
      "score": 1,
      "updatedAt": "2026-05-14T10:02:25-07:00",
      "deletedAt": "2026-05-17T03:24:37.625Z"
    },
    {
      "appId": "686449807",
      "id": "14063954703",
      "author": "ebanofangoso",
      "title": "My account has been deleted twice with no violation",
      "body": "My account has been deleted twice. Both times no violation on my part. When you contact support or volunteers nothing happens. I don’t know how people use this app. I lost all my chats and memories. First time I was able to recover somehow. Now nothing",
      "score": 1,
      "updatedAt": "2026-05-14T08:43:21-07:00",
      "deletedAt": "2026-05-17T03:24:37.625Z"
    },
    {
      "appId": "686449807",
      "id": "14063931219",
      "author": "Melinorobla",
      "title": "My login",
      "body": "Why can I not login in to my account I have been trying to login every since but there is no way longing in",
      "score": 1,
      "updatedAt": "2026-05-14T08:35:54-07:00",
      "deletedAt": "2026-05-17T03:24:37.625Z"
    },
    {
      "appId": "686449807",
      "id": "14063684366",
      "author": "Dar0270",
      "title": "Don’t do it",
      "body": "I downloaded this app long ago and got a bunch of spam emails and text messages immediately after so I deleted it thinking maybe it improved. I downloaded again a week ago. And get multiple text messages a day that are nothing but spam. Very annoying and they should update their privacy.",
      "score": 2,
      "updatedAt": "2026-05-14T07:19:12-07:00",
      "deletedAt": "2026-05-17T03:24:37.625Z"
    },
    {
      "appId": "686449807",
      "id": "14063443540",
      "author": "Mazyarol",
      "title": "Best",
      "body": "Thanks Pavel 🫀🧠",
      "score": 5,
      "updatedAt": "2026-05-14T06:04:53-07:00",
      "deletedAt": "2026-05-17T03:24:37.625Z"
    },
    {
      "appId": "686449807",
      "id": "14063386215",
      "author": "Amer alayed",
      "title": "Please pay attention, it is essential",
      "body": "It appears that the app, in recent updates, does not support accessibility for blind users of voice commentary. Please bring this to our attention so that the problem can be resolved in the next update.",
      "score": 3,
      "updatedAt": "2026-05-14T05:46:38-07:00",
      "deletedAt": "2026-05-17T03:24:37.625Z"
    },
    {
      "appId": "686449807",
      "id": "14063373177",
      "author": "RareRate",
      "title": "New number banned",
      "body": "I got a new phone number. Says my number is banned. What to do?",
      "score": 1,
      "updatedAt": "2026-05-14T05:42:29-07:00",
      "deletedAt": "2026-05-17T03:24:37.625Z"
    },
    {
      "appId": "686449807",
      "id": "14062994000",
      "author": "шур1кк",
      "title": "мяу мяу мяу",
      "body": "я русский и я жму паше руку за то что он делает",
      "score": 5,
      "updatedAt": "2026-05-14T03:29:14-07:00",
      "deletedAt": "2026-05-17T03:24:37.625Z"
    },
    {
      "appId": "686449807",
      "id": "14062639595",
      "author": "amir.f.20",
      "title": "video player",
      "body": "The video player has a problem and is not playing the video properly.",
      "score": 5,
      "updatedAt": "2026-05-14T00:50:12-07:00",
      "deletedAt": "2026-05-17T03:24:37.625Z"
    },
    {
      "appId": "686449807",
      "id": "14062520285",
      "author": "АВРОРА666",
      "title": "Исчезл избранное",
      "body": "Нет доверия - исчезла важная для меня информация, из избранного. Поддержка молчит.\nУдаляю канал. Удаляю важную информацию - доверия 👎",
      "score": 1,
      "updatedAt": "2026-05-13T23:51:41-07:00",
      "deletedAt": "2026-05-17T03:24:37.625Z"
    },
    {
      "appId": "686449807",
      "id": "14062479868",
      "author": "راعبكم",
      "title": "ابة نيو",
      "body": "ليش مايشتغل بلعراق ابلع نجمة وحدة",
      "score": 1,
      "updatedAt": "2026-05-13T23:31:32-07:00",
      "deletedAt": "2026-05-17T03:24:37.625Z"
    },
    {
      "appId": "686449807",
      "id": "14062370239",
      "author": "No need Nike name",
      "title": "Stupidly",
      "body": "too weak if telegram treats world by sending unwanted messages like get free premium but not work to distract sending to my contacts with out ma willing, nasty app ,",
      "score": 1,
      "updatedAt": "2026-05-13T22:34:58-07:00",
      "deletedAt": "2026-05-17T03:24:37.625Z"
    },
    {
      "appId": "686449807",
      "id": "14062282450",
      "author": "SIOPJGHMVBJF😗",
      "title": "Feedback on APP problems",
      "body": "If you use the TeIegram APP software to cut to the background, you can't receive notifications. Even if you return to the desktop, you can't receive notifications. You must click on it, which will affect the user experience. I hope the next version will be paid attention to and optimized so that its background retention can be more stable. Even if you receive important APP messages instead of returning to the desktop, it will not receive it later.",
      "score": 4,
      "updatedAt": "2026-05-13T21:49:18-07:00",
      "deletedAt": "2026-05-17T03:24:37.625Z"
    },
    {
      "appId": "686449807",
      "id": "14062184759",
      "author": "Noomk5",
      "title": "This app is terrible.",
      "body": "This app is terrible. I just signed up and haven’t even used it yet, but my account got banned for no reason.",
      "score": 1,
      "updatedAt": "2026-05-13T20:59:57-07:00",
      "deletedAt": "2026-05-17T03:24:37.625Z"
    },
    {
      "appId": "686449807",
      "id": "14061700552",
      "author": "NinjaOwlKitsune",
      "title": "Fix your app",
      "body": "Fix your app",
      "score": 1,
      "updatedAt": "2026-05-13T17:26:08-07:00",
      "deletedAt": "2026-05-17T03:24:37.625Z"
    },
    {
      "appId": "686449807",
      "id": "14061293222",
      "author": "zuxt",
      "title": "icgg",
      "body": "меня взломали из за подключения прокси ☺️",
      "score": 4,
      "updatedAt": "2026-05-13T14:35:48-07:00",
      "deletedAt": "2026-05-17T03:24:37.625Z"
    },
    {
      "appId": "686449807",
      "id": "14061042216",
      "author": "Jay-moneyGold",
      "title": "Asking for money for reinstallation",
      "body": "I had to delete and reinstall Telegram because it was taking up so much space on my phone, now in order for it to work, it is asking for money.  “Support Via Telegram Premium”. Completely unacceptable.  No other messaging app ever asked for money.  I’m super disappointed",
      "score": 1,
      "updatedAt": "2026-05-13T12:57:42-07:00",
      "deletedAt": "2026-05-17T03:24:37.625Z"
    },
    {
      "appId": "686449807",
      "id": "14060949264",
      "author": "Shervinetto",
      "title": "One",
      "body": "The best of al time!",
      "score": 5,
      "updatedAt": "2026-05-13T12:23:02-07:00",
      "deletedAt": "2026-05-17T03:24:37.625Z"
    },
    {
      "appId": "686449807",
      "id": "14060948796",
      "author": "2pumba5",
      "title": "кайф",
      "body": "нормас пацаны",
      "score": 5,
      "updatedAt": "2026-05-13T12:22:51-07:00",
      "deletedAt": "2026-05-17T03:24:37.625Z"
    },
    {
      "appId": "686449807",
      "id": "14060805641",
      "author": "totototititottitititito",
      "title": "I did not receive any SMS verification code.",
      "body": "I did not receive any SMS verification code.",
      "score": 1,
      "updatedAt": "2026-05-13T11:31:01-07:00",
      "deletedAt": "2026-05-17T03:24:37.625Z"
    },
    {
      "appId": "686449807",
      "id": "14060593906",
      "author": "Jthiha",
      "title": "Can't open chat anymore after update!",
      "body": "iPhone 13 - iOS 26.3.1. Update the latest version and can't open the chat box anymore. And NO! Not because of content restriction or anything. Please fix.",
      "score": 1,
      "updatedAt": "2026-05-13T10:17:26-07:00",
      "deletedAt": "2026-05-17T03:24:37.625Z"
    },
    {
      "appId": "686449807",
      "id": "14060517371",
      "author": "Peaches thoughts",
      "title": "Terrible app with nothing but scammers, and illegal abuse being advertised. PLEASE PLEASE READ",
      "body": "For one the app is full of scammers. I was in the app and another account started impersonating me- using my pictures to scam people. I contacted support and the bots, along with writing multiple emails over the span of 3 years to resolve this. The account made fake channels of me- although support never responded 2 of the channels did get deleted shortly after. But they just make another channel. The 3rd one they made- I’ve reached out about for over a year now. Still no response and this time no action. They chose to leave the whole account up- even though the profile itself was also posting my to story and mimicked my profile. And since they just leave the account up it allows them to continue making new channels. I’ve requested both to be taken down, submitted proof of who I am. Proof the account is very fake. (My Id, my full name, every social I have, and even a video of myself explaining everything.) the owners of this app\nDo not care. They would rather get the 4$ monthly subscription the account pays to pretend to be me and scam normal users than delete the account. This is a very common problem on this app- I know many people currently being impersonated and telegram just does not care. If you reach out to support volunteers they never respond.  The scam bot never responds. The emails for scam and abuse do nothing. The app claims they prioritize safety and privacy and gives options to disable sharing and screen recording of the things you post.. then they have bots in the app to just bypass that to steal your posts. No\nSuch thing as privacy. Not only that but there is so much illegal things posted through this app. Child porn. Animal abuse. Selling dope. Arraignment of illegal things in general.. the same spam account I came across posting advertising selling child porn on their story 2 years ago and reported- and had many people go report.. IS STILL UP AND POSTING IT. The creators of this app really do not care about their users being scammed or harassed. They don’t care about their exploitation or abuse being openly exposed on this app. As long as the account is paying that 4$ monthly subscription subscription.. they will leave it up. It’s disgusting.",
      "score": 1,
      "updatedAt": "2026-05-13T09:51:54-07:00",
      "deletedAt": "2026-05-17T03:24:37.625Z"
    },
    {
      "appId": "686449807",
      "id": "14060421323",
      "author": "Smarti0s",
      "title": "Точка возврата",
      "body": "С недавним обновлением пропала возможность быстро скроллить вверх по тапу (например по островку)\niPhone 14 Pro, иногда нужно вернуться наверх, но приходится скроллить вручную",
      "score": 4,
      "updatedAt": "2026-05-13T09:20:20-07:00",
      "deletedAt": "2026-05-17T03:24:37.625Z"
    },
    {
      "appId": "686449807",
      "id": "14060323406",
      "author": "Arman in Iran",
      "title": "Best",
      "body": "It’s best app in the earth",
      "score": 5,
      "updatedAt": "2026-05-13T08:49:04-07:00",
      "deletedAt": "2026-05-17T03:24:37.625Z"
    },
    {
      "appId": "686449807",
      "id": "14060270999",
      "author": "Can’tThinkOfAnyNicknames",
      "title": "Lovely",
      "body": "Great app, been using it since 2016, so reliable, keep up the good work telegram team!",
      "score": 5,
      "updatedAt": "2026-05-13T08:32:31-07:00",
      "deletedAt": "2026-05-17T03:24:37.625Z"
    },
    {
      "appId": "686449807",
      "id": "14060194796",
      "author": "SadeghSpy",
      "title": "Best",
      "body": "Besttt",
      "score": 5,
      "updatedAt": "2026-05-13T08:08:36-07:00",
      "deletedAt": "2026-05-17T03:24:37.625Z"
    },
    {
      "appId": "686449807",
      "id": "14059869598",
      "author": "lasvelez",
      "title": "Saludo hola",
      "body": "Como pasaste el dia ? Bien heart",
      "score": 5,
      "updatedAt": "2026-05-13T06:27:54-07:00",
      "deletedAt": "2026-05-17T03:24:37.625Z"
    },
    {
      "appId": "686449807",
      "id": "14059612817",
      "author": "Ballons77",
      "title": "@ballons77",
      "body": "Лучшее приложение",
      "score": 5,
      "updatedAt": "2026-05-13T05:04:09-07:00",
      "deletedAt": "2026-05-17T03:24:37.625Z"
    },
    {
      "appId": "686449807",
      "id": "14059588975",
      "author": "Jeasuuuuus",
      "title": "Best messenger ever",
      "body": "Thanks Paul",
      "score": 5,
      "updatedAt": "2026-05-13T04:55:59-07:00",
      "deletedAt": "2026-05-17T03:24:37.625Z"
    },
    {
      "appId": "686449807",
      "id": "14059366333",
      "author": "sul111111",
      "title": "Скорость воспроизведения аудио",
      "body": "Можно решить проблему нормального переключения скорости воспроизведения аудио в телеграм?\nПо несколько раз приходится тыкать в эту щель 1х,1,5х,2х.\nСделать полноценную кнопку что ли😂 \nДико раздражает",
      "score": 5,
      "updatedAt": "2026-05-13T03:32:35-07:00",
      "deletedAt": "2026-05-17T03:24:37.625Z"
    },
    {
      "appId": "686449807",
      "id": "14059304051",
      "author": "soheil9898",
      "title": "❤️ best app for ever",
      "body": "❤️ best app for ever 🚀🚀",
      "score": 5,
      "updatedAt": "2026-05-13T03:05:58-07:00",
      "deletedAt": "2026-05-17T03:24:37.625Z"
    },
    {
      "appId": "686449807",
      "id": "14059123703",
      "author": "StormFatima",
      "title": "Bad",
      "body": "I have used it before , it was good , i changed my iphone before 4 months and till now not working what a bad application !!!",
      "score": 1,
      "updatedAt": "2026-05-13T01:40:59-07:00",
      "deletedAt": "2026-05-17T03:24:37.625Z"
    },
    {
      "appId": "686449807",
      "id": "14059101651",
      "author": "Tingerorig",
      "title": "The best app for communication",
      "body": "Very comfortable and functional",
      "score": 5,
      "updatedAt": "2026-05-13T01:30:07-07:00",
      "deletedAt": "2026-05-17T03:24:37.625Z"
    },
    {
      "appId": "686449807",
      "id": "14058964128",
      "author": "Morttoo",
      "title": "Speed, innovation, security",
      "body": "I’m using telegram for 10 years, and I can say it’s the best messenger",
      "score": 5,
      "updatedAt": "2026-05-13T00:21:01-07:00",
      "deletedAt": "2026-05-17T03:24:37.625Z"
    },
    {
      "appId": "686449807",
      "id": "14058570468",
      "author": "Aiza Bee",
      "title": "This app sucks",
      "body": "This app sucks to the highest degree. I’ve been using it in the past, and then I change phones after changing phones and installing it on the new phone it said the cost of SMS is so high that in order to enable your profile, we must charge you $1.13 per week. Obviously,  obviously, I scoffed. After considering ,  I will use other apps. stop it",
      "score": 1,
      "updatedAt": "2026-05-12T21:02:10-07:00",
      "deletedAt": "2026-05-17T03:24:37.625Z"
    },
    {
      "appId": "686449807",
      "id": "14057755688",
      "author": "Kamika_065",
      "title": "blame hoyo",
      "body": "genshin give us our primogems wth",
      "score": 1,
      "updatedAt": "2026-05-12T15:11:00-07:00",
      "deletedAt": "2026-05-17T03:24:37.625Z"
    },
    {
      "appId": "686449807",
      "id": "14057110416",
      "author": "Ella Jarred",
      "title": "Paid feature just bad",
      "body": "Allows spam even if you pay premium.\n\nI’m in a Telegram group associated to a channel. On a daily basis (and often more than once a day) a spam bot simultaneously answers to the latest 50 channel posts with the same spam message, and the accounts used to send those messages (which inevitably flood the group) are always Premium accounts. If Premium accounts can write to you anyway, there is no reason to pay for that.",
      "score": 1,
      "updatedAt": "2026-05-12T11:08:25-07:00",
      "deletedAt": "2026-05-17T03:24:37.625Z"
    },
    {
      "appId": "686449807",
      "id": "14056727379",
      "author": "Aetina",
      "title": "Liquid glass ui even when I have not upgraded to ios 26",
      "body": "Seriously… the UI is awful and i hope it goes away. It shifts on the screen too much and just makes the UX confusing.\n\nI’ll rate one star til it’s removed. I’m mostly off TG but need it for a few friends… the UI change is not doing it any favors",
      "score": 1,
      "updatedAt": "2026-05-12T09:01:44-07:00",
      "deletedAt": "2026-05-17T03:24:37.625Z"
    },
    {
      "appId": "686449807",
      "id": "14056475915",
      "author": "nyan1828",
      "title": "мало кастомизации",
      "body": "добавьте возможность  убирать liquid glass и еще блльш настроек",
      "score": 3,
      "updatedAt": "2026-05-12T07:43:43-07:00",
      "deletedAt": "2026-05-17T03:24:37.625Z"
    },
    {
      "appId": "686449807",
      "id": "14055555061",
      "author": "لكنما",
      "title": "س",
      "body": "عدلو على ستوري يكون اكثر من ١٠ ستوريات بالشهر",
      "score": 2,
      "updatedAt": "2026-05-12T02:14:45-07:00",
      "deletedAt": "2026-05-17T03:24:37.625Z"
    },
    {
      "appId": "686449807",
      "id": "14055016474",
      "author": "Campaña Anti Anuncios",
      "title": "Hambreados",
      "body": "Ahora te cobran por iniciar sesión, que sigue después?, que te cobren por respirar?, váyanse a la mrd 🥀🥀🥀🥀🥀🥀🥀",
      "score": 1,
      "updatedAt": "2026-05-11T21:39:45-07:00",
      "deletedAt": "2026-05-17T03:24:37.625Z"
    },
    {
      "appId": "686449807",
      "id": "14054224753",
      "author": "PonyMaTW",
      "title": "Scammer’s heaven",
      "body": "T",
      "score": 1,
      "updatedAt": "2026-05-11T15:52:25-07:00",
      "deletedAt": "2026-05-17T03:24:37.625Z"
    },
    {
      "appId": "686449807",
      "id": "14054121883",
      "author": "405020",
      "title": ".",
      "body": "Bro better than whatsapp in everything",
      "score": 5,
      "updatedAt": "2026-05-11T15:09:32-07:00",
      "deletedAt": "2026-05-17T03:24:37.625Z"
    },
    {
      "appId": "686449807",
      "id": "14053987203",
      "author": "STRELAVPN",
      "title": "Паша верни стену",
      "body": "Пашка ты молодец топ приложение но стену вернуть надо)",
      "score": 5,
      "updatedAt": "2026-05-11T14:15:09-07:00",
      "deletedAt": "2026-05-17T03:24:37.625Z"
    },
    {
      "appId": "686449807",
      "id": "14068939466",
      "author": "خالد الحبش",
      "title": "من فلسطين",
      "body": "سيء لأنه يطلب رسوم تسجيل واحد دولار",
      "score": 1,
      "updatedAt": "2026-05-15T16:43:34-07:00",
      "deletedAt": null
    },
    {
      "appId": "686449807",
      "id": "14068908147",
      "author": "Xiao9啊",
      "title": "登录要钱验证，离谱",
      "body": "，",
      "score": 1,
      "updatedAt": "2026-05-15T16:30:37-07:00",
      "deletedAt": null
    },
    {
      "appId": "686449807",
      "id": "14068870519",
      "author": "Luh gav",
      "title": "App",
      "body": "This lady tried to leak me and our messages",
      "score": 1,
      "updatedAt": "2026-05-15T16:15:08-07:00",
      "deletedAt": null
    },
    {
      "appId": "686449807",
      "id": "14068617920",
      "author": "okiebama",
      "title": "Lost contact",
      "body": "Irritated",
      "score": 2,
      "updatedAt": "2026-05-15T14:31:39-07:00",
      "deletedAt": null
    }
  ]
}
